Metadata-Version: 1.0
Name: covid-weather
Version: 0.1
Summary: Tools for working with covid-19 data and weather
Home-page: https://github.com/zack-kimble/covid
Author: Zachary Kimble
Author-email: zkimble@gmail.com
License: MIT
Platform: UNKNOWN
